CHANGELOG.txt
LICENSE.txt
MANIFEST.in
README.txt
__init__.py
setup.py
Topsis-IshikaGoel-101803407/topsis.py
Topsis_IshikaGoel_101803407.egg-info/PKG-INFO
Topsis_IshikaGoel_101803407.egg-info/SOURCES.txt
Topsis_IshikaGoel_101803407.egg-info/dependency_links.txt
Topsis_IshikaGoel_101803407.egg-info/requires.txt
Topsis_IshikaGoel_101803407.egg-info/top_level.txt
venv/lib/python3.8/site-packages/easy_install.py
venv/lib/python3.8/site-packages/six.py
venv/lib/python3.8/site-packages/_distutils_hack/__init__.py
venv/lib/python3.8/site-packages/_distutils_hack/override.py
venv/lib/python3.8/site-packages/dateutil/__init__.py
venv/lib/python3.8/site-packages/dateutil/_common.py
venv/lib/python3.8/site-packages/dateutil/_version.py
venv/lib/python3.8/site-packages/dateutil/easter.py
venv/lib/python3.8/site-packages/dateutil/relativedelta.py
venv/lib/python3.8/site-packages/dateutil/rrule.py
venv/lib/python3.8/site-packages/dateutil/tzwin.py
venv/lib/python3.8/site-packages/dateutil/utils.py
venv/lib/python3.8/site-packages/dateutil/parser/__init__.py
venv/lib/python3.8/site-packages/dateutil/parser/_parser.py
venv/lib/python3.8/site-packages/dateutil/parser/isoparser.py
venv/lib/python3.8/site-packages/dateutil/tz/__init__.py
venv/lib/python3.8/site-packages/dateutil/tz/_common.py
venv/lib/python3.8/site-packages/dateutil/tz/_factories.py
venv/lib/python3.8/site-packages/dateutil/tz/tz.py
venv/lib/python3.8/site-packages/dateutil/tz/win.py
venv/lib/python3.8/site-packages/dateutil/zoneinfo/__init__.py
venv/lib/python3.8/site-packages/dateutil/zoneinfo/rebuild.py
venv/lib/python3.8/site-packages/numpy/LICENSE.txt
venv/lib/python3.8/site-packages/numpy/__config__.py
venv/lib/python3.8/site-packages/numpy/__init__.py
venv/lib/python3.8/site-packages/numpy/_distributor_init.py
venv/lib/python3.8/site-packages/numpy/_globals.py
venv/lib/python3.8/site-packages/numpy/_pytesttester.py
venv/lib/python3.8/site-packages/numpy/conftest.py
venv/lib/python3.8/site-packages/numpy/ctypeslib.py
venv/lib/python3.8/site-packages/numpy/dual.py
venv/lib/python3.8/site-packages/numpy/matlib.py
venv/lib/python3.8/site-packages/numpy/setup.py
venv/lib/python3.8/site-packages/numpy/version.py
venv/lib/python3.8/site-packages/numpy-1.19.4.dist-info/LICENSE.txt
venv/lib/python3.8/site-packages/numpy-1.19.4.dist-info/LICENSES_bundled.txt
venv/lib/python3.8/site-packages/numpy-1.19.4.dist-info/entry_points.txt
venv/lib/python3.8/site-packages/numpy-1.19.4.dist-info/top_level.txt
venv/lib/python3.8/site-packages/pandas-1.1.4.dist-info/entry_points.txt
venv/lib/python3.8/site-packages/pandas-1.1.4.dist-info/top_level.txt
venv/lib/python3.8/site-packages/pip-20.2.4.dist-info/LICENSE.txt
venv/lib/python3.8/site-packages/pip-20.2.4.dist-info/entry_points.txt
venv/lib/python3.8/site-packages/pip-20.2.4.dist-info/top_level.txt
venv/lib/python3.8/site-packages/python_dateutil-2.8.1.dist-info/top_level.txt
venv/lib/python3.8/site-packages/pytz-2020.4.dist-info/LICENSE.txt
venv/lib/python3.8/site-packages/pytz-2020.4.dist-info/top_level.txt
venv/lib/python3.8/site-packages/setuptools-50.3.2.dist-info/dependency_links.txt
venv/lib/python3.8/site-packages/setuptools-50.3.2.dist-info/entry_points.txt
venv/lib/python3.8/site-packages/setuptools-50.3.2.dist-info/top_level.txt
venv/lib/python3.8/site-packages/six-1.15.0.dist-info/top_level.txt