Metadata-Version: 1.1
Name: Topsis-IshikaGoel-101803407
Version: 0.0.1
Summary: It is method to find out best value among different data using mathematical calculation.
Home-page: UNKNOWN
Author: Ishika Goel
Author-email: ishika.goel2010@gmail.com
License: UNKNOWN
Keywords: topsis
Platform: UNKNOWN
Classifier: Operating System :: OS Independent
Classifier: License :: OSI Approved :: MIT License
Classifier: Programming Language :: Python :: 3
